poetry_plugin_pypi_mirror/__init__.py
poetry_plugin_pypi_mirror/plugins.py
poetry_plugin_pypi_mirror/py.typed
poetry_plugin_pypi_mirror-0.6.3.dist-info/METADATA
poetry_plugin_pypi_mirror-0.6.3.dist-info/WHEEL
poetry_plugin_pypi_mirror-0.6.3.dist-info/entry_points.txt
poetry_plugin_pypi_mirror-0.6.3.dist-info/licenses/LICENSE
poetry_plugin_pypi_mirror-0.6.3.dist-info/RECORD
