Metadata-Version: 2.4
Name: poetry-plugin-pypi-mirror
Version: 0.6.3
Summary: Poetry plugin that adds support for pypi.org mirrors and pull-through caches
License: BSD-3-Clause
License-File: LICENSE
Keywords: packaging,poetry,pypi
Author: Jacob Henner
Author-email: code@ventricle.us
Requires-Python: >=3.9.0,<4.0.0
Classifier: License :: OSI Approved :: BSD License
Classifier: Programming Language :: Python :: 3
Classifier: Programming Language :: Python :: 3.9
Classifier: Programming Language :: Python :: 3.10
Classifier: Programming Language :: Python :: 3.11
Classifier: Programming Language :: Python :: 3.12
Classifier: Programming Language :: Python :: 3.13
Classifier: Programming Language :: Python :: 3.14
Requires-Dist: poetry (>=2.1,<2.4)
Project-URL: Homepage, https://github.com/arcesium/poetry-plugin-pypi-mirror
Project-URL: Repository, https://github.com/arcesium/poetry-plugin-pypi-mirror
